README.md
setup.cfg
setup.py
fill_missing_values_ashwin/__init__.py
fill_missing_values_ashwin/missing_values.py
fill_missing_values_ashwin.egg-info/PKG-INFO
fill_missing_values_ashwin.egg-info/SOURCES.txt
fill_missing_values_ashwin.egg-info/dependency_links.txt
fill_missing_values_ashwin.egg-info/top_level.txt