Metadata-Version: 2.1
Name: fill-missing-values-ashwin
Version: 0.0.3
Summary: A small package for filling missing values in the given dataset
Home-page: https://github.com/ash-1999/fill_missing_values_ashwin
Author: ashwin_menon
Author-email: ashwin.s.menon1999@gmail.com
License: UNKNOWN
Download-URL: https://github.com/ash-1999/fill_missing_values_ashwin/archive/0.0.3.tar.gz
Platform: UNKNOWN
Classifier: Programming Language :: Python :: 3
Classifier: License :: OSI Approved :: MIT License
Classifier: Operating System :: OS Independent
Requires-Python: >=3.6
